polywrap_result/__init__.py
polywrap_result-0.1.0.dist-info/WHEEL
polywrap_result-0.1.0.dist-info/METADATA
polywrap_result-0.1.0.dist-info/RECORD
