Metadata-Version: 2.1
Name: polywrap-result
Version: 0.1.0
Summary: Result object
Author: Danilo Bargen
Author-email: mail@bargen.dev
Requires-Python: >=3.10,<4.0
Classifier: Programming Language :: Python :: 3
Classifier: Programming Language :: Python :: 3.10
Classifier: Programming Language :: Python :: 3.11
